LICENSE.txt
MANIFEST.in
Makefile
README.rst
pytest.ini
setup.py
docs/Makefile
docs/make.bat
docs/source/conf.py
docs/source/index.rst
docs/source/installation.rst
docs/source/usage.rst
python_redict.egg-info/PKG-INFO
python_redict.egg-info/SOURCES.txt
python_redict.egg-info/dependency_links.txt
python_redict.egg-info/requires.txt
python_redict.egg-info/top_level.txt
redict/__init__.py
redict/base.py
redict/remappers/__init__.py
redict/remappers/dict.py
redict/remappers/json.py
redict/tests/__init__.py
redict/tests/test_base.py
redict/tests/test_json.py
redict/tests/test_utils.py
redict/utils/__init__.py
redict/utils/minify_json.py