Metadata-Version: 1.1
Name: python-redict
Version: 0.2
Summary: A Python dictionary key remapper
Home-page: https://github.com/lockwooddev/python-redict
Author: Carlo Smouter
Author-email: lockwooddev@gmail.com
License: MIT
Keywords: python,dictionary,remap,keys,remapper
Platform: UNKNOWN
Classifier: Development Status :: 4 - Beta
Classifier: Intended Audience :: Developers
Classifier: License :: OSI Approved :: MIT License
Classifier: Operating System :: OS Independent
Classifier: Programming Language :: Python
Classifier: Programming Language :: Python :: 2.7
Classifier: Programming Language :: Python :: 3.4
Classifier: Topic :: Internet :: WWW/HTTP
